kafka_dataclasses/__init__.py
kafka_dataclasses/skeleton.py
kafka_dataclasses/core/__init__.py
kafka_python_dataclasses-2022.4.22.3.dist-info/LICENSE.txt
kafka_python_dataclasses-2022.4.22.3.dist-info/METADATA
kafka_python_dataclasses-2022.4.22.3.dist-info/WHEEL
kafka_python_dataclasses-2022.4.22.3.dist-info/top_level.txt
kafka_python_dataclasses-2022.4.22.3.dist-info/RECORD
