Metadata-Version: 2.1
Name: kafka-python-dataclasses
Version: 2022.4.22.3
Summary: Add a short description here!
Home-page: https://github.com/pyscaffold/pyscaffold/
Author: Collin Sage
Author-email: 3229549+MrSage@users.noreply.github.com
License: MIT
Project-URL: Documentation, https://pyscaffold.org/
Project-URL: Source, https://github.com/MrSage/python-kafka-dataclasses
Project-URL: Changelog, https://raw.githubusercontent.com/MrSage/python-kafka-dataclasses/main/CHANGELOG.rst
Project-URL: Tracker, https://github.com/MrSage/python-kafka-dataclasses/issues
Project-URL: Download, https://pypi.org/project/kafka-python-dataclasses/
Platform: any
Classifier: Development Status :: 4 - Beta
Classifier: Programming Language :: Python
License-File: LICENSE.txt
Requires-Dist: kafka-python
Requires-Dist: cattrs
Requires-Dist: importlib-metadata ; python_version < "3.8"
Provides-Extra: testing
Requires-Dist: setuptools ; extra == 'testing'
Requires-Dist: pytest ; extra == 'testing'
Requires-Dist: pytest-cov ; extra == 'testing'
Requires-Dist: pytest-random-order ; extra == 'testing'
